<odoo>
    <data noupdate="0">
        <!-- customer invoice -->
        <record model="ir.module.category" id="sale_order_approvel_request_access">
            <field name="name">Sale Order Approval</field>
            <field name="description">User access level for custom modul</field>
            <field name="sequence">4</field>
        </record>

        <record id="sale_order_approval" model="res.groups">
            <field name="name">Sale Order Approval</field>
            <field name="category_id" ref="partner_credit_limit.sale_order_approvel_request_access" />
        </record>
    </data>
</odoo>